[
  {
    "id": "79cd3b77-69d6-465b-8daf-116accac51de",
    "firstName": "Claudine",
    "lastName": "Adams",
    "emailAddress": "claudine.adams@newzoescitt.co.uk",
    "organisations": [
      {
        "org": {
          "id": "9f79617a-2702-48b1-aef5-ebdd35b74596",
          "name": "Wren Academy",
          "isAccreditedBody": false
        },
        "permissions": {
          "manageOrganisation": true,
          "manageUsers": true,
          "makeDecisions": true,
          "viewSafeguardingInformation": true,
          "viewDiversityInformation": true
        }
      },
      {
        "org": {
          "id": "df52d8fe-17bb-443e-93c4-8c7ac15c2352",
          "name": "Kingston University",
          "isAccreditedBody": true
        },
        "permissions": {
          "manageOrganisation": true,
          "manageUsers": true,
          "makeDecisions": true,
          "viewSafeguardingInformation": true,
          "viewDiversityInformation": true
        }
      }
    ]
  },
  {
    "id": "8ec30733-45c5-40a9-bdc1-da41605eb2ca",
    "firstName": "Duncan",
    "lastName": "Patricks",
    "emailAddress": "duncan.patricks@newzoescitt.co.uk",
    "organisations": [
      {
        "org": {
          "id": "9f79617a-2702-48b1-aef5-ebdd35b74596",
          "name": "Wren Academy",
          "isAccreditedBody": false
        }
      }
    ]
  }
]